{"404.md":"d96187bf","changelog.md":"86d43f95","readme.md":"1407b6af","academy_cases_index.md":"8fa11a66","academy_educators_index.md":"eaea8199","academy_index.md":"6a0c0303","academy_materials_index.md":"9f82b190","academy_materials_ru_colab-20_index.md":"3b8a7b56","academy_materials_ru_index.md":"9e3df213","academy_materials_ru_namm-19_index.md":"b306cc81","academy_materials_ru_skillbox_index.md":"9b5b9e9d","contacts_author_index.md":"1f6e3b6f","contacts_index.md":"bb27c6a1","contacts_official_index.md":"6fb95f52","index.md":"54b582f4","practice_chord_array_index.md":"17bb629d","practice_chord_fifths_index.md":"99715396","practice_chord_finder_index.md":"67b72245","practice_chord_index.md":"864dd2ea","practice_chord_modes_index.md":"b8ecdc56","practice_chord_scales_index.md":"af18c12d","practice_chord_tabs_index.md":"abea1d18","practice_chroma_browser_index.md":"79b582ba","practice_chroma_compass_index.md":"61bb531a","practice_chroma_index.md":"f79e1d22","practice_chroma_profile_index.md":"81834166","practice_chroma_roll_index.md":"1302f16e","practice_chroma_split_index.md":"bddafb95","practice_chroma_waveform_index.md":"b1526afb","practice_color_cmyk_index.md":"55215d96","practice_color_hsl_index.md":"8c9200fb","practice_color_index.md":"d456bd06","practice_color_lab_index.md":"fb955693","practice_color_rgb_index.md":"39a763bc","practice_experiments_ambience_index.md":"d9525f1c","practice_experiments_connect_circle_index.md":"31ad6f30","practice_experiments_connect_index.md":"8004de9c","practice_experiments_dev_index.md":"53367bfb","practice_experiments_fretboard_index.md":"ecd73a86","practice_experiments_index.md":"b84b4763","practice_experiments_lab_index.md":"ca37200c","practice_experiments_other_index.md":"cf1d4aa1","practice_experiments_paper_index.md":"07bbe469","practice_experiments_spectrum_index.md":"6a5e079b","practice_experiments_touchme_index.md":"a4d8a117","practice_index.md":"9a7117ee","practice_midi_index.md":"d3bd02f9","practice_midi_log_index.md":"0a86fbde","practice_midi_monitor_index.md":"402d764c","practice_midi_radar_index.md":"8ed4c123","practice_midi_recorder_index.md":"45945eca","practice_midi_roll_index.md":"f24906ac","practice_midi_router_index.md":"e86bf365","practice_midi_visualizer_index.md":"f98cfeaa","practice_pitch_drone_index.md":"f5a50d31","practice_pitch_grid_index.md":"a07e64c0","practice_pitch_index.md":"d691635f","practice_pitch_roll_index.md":"4d112559","practice_pitch_spectrogram_index.md":"ec2560ab","practice_pitch_table_index.md":"7dd022a9","practice_pitch_tuner_index.md":"bc303f62","practice_rhythm_circle_index.md":"c5baa5ec","practice_rhythm_index.md":"68136e78","practice_rhythm_loops_index.md":"5f526e00","practice_rhythm_noise_index.md":"83781959","practice_rhythm_sequencer_index.md":"b07fca27","practice_sound_dissonance_index.md":"f3908fef","practice_sound_index.md":"741b67fa","practice_sound_loudness_index.md":"4d3e6a09","practice_sound_monochord_index.md":"8423fbb3","practice_sound_overtones_index.md":"d177f165","shop_fretboard_a5multi_index.md":"b89dc7f6","shop_fretboard_guitar_index.md":"1b642a6b","shop_fretboard_index.md":"20e787fd","shop_fretboard_tenor_index.md":"d8b847a4","shop_fretboard_ukulele_index.md":"bfb5614c","shop_index.md":"696ba4f6","shop_keys_108_index.md":"a17a0a80","shop_keys_a5max_index.md":"37802253","shop_keys_index.md":"dcad7389","shop_keys_op-1_index.md":"6d67a09b","shop_keys_op-1_matte_index.md":"bda38e91","shop_keys_piano_index.md":"35411ac9","shop_keys_universal_index.md":"84296a88","shop_memo_a4_index.md":"03919ff2","shop_memo_a5_index.md":"7b1a0c99","shop_memo_holocircle_index.md":"0e4dbea1","shop_memo_index.md":"3e8ffff3","support_contribute_index.md":"a9520ec7","support_donate_index.md":"9d5c06f2","support_follow_index.md":"ec23ef59","support_index.md":"ee908ff6","theory_chords_5more_index.md":"0acf3eeb","theory_chords_clusters_index.md":"bd2c7475","theory_chords_index.md":"555beeb2","theory_chords_tetrads_index.md":"e9dda003","theory_chords_triads_index.md":"d12db631","theory_color_index.md":"1342327e","theory_color_interplay_index.md":"d4cff87f","theory_color_interplay_spectrum_index.md":"6490902c","theory_color_interplay_synesthesia_index.md":"54ac4786","theory_color_light_em-waves_index.md":"86bbc285","theory_color_light_index.md":"f232fd45","theory_color_light_spectrum_index.md":"7e45c818","theory_color_light_sun_index.md":"25f998a4","theory_color_models_additive_index.md":"1636370d","theory_color_models_index.md":"8fc2399b","theory_color_models_perceptual_index.md":"8c409eee","theory_color_models_subtractive_index.md":"20beda9c","theory_color_names_index.md":"22aa0ad9","theory_color_perception_index.md":"9ce798af","theory_composition_composers_index.md":"83d29d80","theory_composition_form_index.md":"cbacb8f4","theory_composition_generative_index.md":"537b2972","theory_composition_index.md":"90d854e6","theory_composition_serialism_index.md":"fbe03a0d","theory_composition_song_index.md":"7607aa61","theory_composition_texture_index.md":"5a8c62cc","theory_harmony_chord-scale_index.md":"ff2aca04","theory_harmony_index.md":"1ef9b091","theory_harmony_modulation_index.md":"2cadc0b3","theory_harmony_movement_index.md":"43e3f53d","theory_harmony_non-chord_index.md":"39e139c1","theory_harmony_polytonality_index.md":"0620f661","theory_harmony_progressions_index.md":"514826f7","theory_harmony_study_index.md":"573c6f1c","theory_index.md":"d70807a5","theory_intervals_cycles_index.md":"59b6f7bb","theory_intervals_dissonance_index.md":"9335a510","theory_intervals_emancipation_index.md":"5e9ad6b1","theory_intervals_fifth-fourth_index.md":"fecfa8be","theory_intervals_index.md":"a6d1b817","theory_intervals_second-seventh_index.md":"2e85533a","theory_intervals_third-sixth_index.md":"7917d78a","theory_intervals_unison-octave_index.md":"0791232a","theory_melody_articulation_index.md":"38f6d131","theory_melody_drone_index.md":"10f3fd02","theory_melody_index.md":"d633ba66","theory_melody_motion_index.md":"777ce97f","theory_melody_singing_index.md":"b85770f9","theory_melody_study_index.md":"e682b5c2","theory_notes_alternative_abc_index.md":"bf4eaa62","theory_notes_alternative_bilinear_index.md":"69bfe047","theory_notes_alternative_chromatic-staff_index.md":"8bbc200b","theory_notes_alternative_dodeka_index.md":"233b6848","theory_notes_alternative_index.md":"5a50092d","theory_notes_alternative_integer_index.md":"d23b1218","theory_notes_alternative_klavar_index.md":"0a9590e5","theory_notes_alternative_midi_index.md":"01dceda5","theory_notes_alternative_numbered_index.md":"054a4377","theory_notes_alternative_parsons_index.md":"4d464ed5","theory_notes_alternative_piano-roll_index.md":"4e2a6fff","theory_notes_alternative_scientific_index.md":"908b8714","theory_notes_alternative_tabulature_index.md":"169c834e","theory_notes_color_index.md":"cc30f550","theory_notes_evolution_index.md":"b59db516","theory_notes_index.md":"ae7cc664","theory_notes_national_index.md":"e63f9d67","theory_notes_solmization_index.md":"dd2e29d6","theory_notes_staff_index.md":"e7c2c078","theory_notes_staff_sight-reading_index.md":"4ae33046","theory_notes_temperaments_equal_index.md":"6251f70a","theory_notes_temperaments_index.md":"e3a2ba48","theory_notes_temperaments_just_index.md":"59f8b208","theory_notes_temperaments_pythagorean_index.md":"276e5efb","theory_notes_temperaments_tunings_index.md":"66c31ace","theory_resources_index.md":"376ab90c","theory_rhythm_counting_index.md":"1c2e006c","theory_rhythm_groove_index.md":"f9806bfb","theory_rhythm_index.md":"4ff1a72b","theory_rhythm_meter_complex_index.md":"f902d081","theory_rhythm_meter_compound_index.md":"ce43ff6a","theory_rhythm_meter_index.md":"b2805975","theory_rhythm_meter_simple_index.md":"274a6e9a","theory_rhythm_meter_time_index.md":"15695ea2","theory_rhythm_pulse_index.md":"75cd1da1","theory_rhythm_rudiments_index.md":"a5dd1eed","theory_rhythm_study_index.md":"68901d85","theory_rhythm_system_clave_index.md":"96fb2554","theory_rhythm_system_crossbeat_index.md":"dd401e37","theory_rhythm_system_euclidean_index.md":"d8f6fdea","theory_rhythm_system_flamenco_index.md":"53d5ab47","theory_rhythm_system_index.md":"2a8324ff","theory_rhythm_system_tala_index.md":"ab855480","theory_scales_degrees_index.md":"9f92e124","theory_scales_diatonic_index.md":"5d72c25f","theory_scales_index.md":"0f162099","theory_scales_pentatonic_index.md":"3a67561a","theory_scales_raga_index.md":"e4085546","theory_scales_study_index.md":"5eb29142","theory_scales_symmetrical_index.md":"7c6724dd","theory_sound_hearing_index.md":"50f90366","theory_sound_index.md":"95c21c23","theory_sound_nature_index.md":"5c43688b","theory_sound_pitch_index.md":"27fa8732","theory_sound_psychoacoustics_illusions_index.md":"c80fc616","theory_sound_psychoacoustics_index.md":"946e81f3","theory_sound_timbre_index.md":"fe076182"}
