{"404.md":"7dba56ec","readme.md":"0081fca4","academy_educators_index.md":"e90b98b6","academy_index.md":"b2cb9bee","academy_materials_index.md":"16e082e3","academy_materials_ru_colab-20_index.md":"640e4448","academy_materials_ru_index.md":"07026eb7","academy_materials_ru_namm-19_index.md":"920244ed","academy_materials_ru_skillbox_index.md":"9c0a99c0","academy_partners_index.md":"f2beb1aa","apps_chord_array_index.md":"757bd2f1","apps_chord_fifths_index.md":"218482c5","apps_chord_finder_index.md":"b3829171","apps_chord_index.md":"e4504334","apps_chord_modes_index.md":"b3a87072","apps_chord_tabs_index.md":"3ae21b8d","apps_chroma_browser_index.md":"2b472bc8","apps_chroma_compass_index.md":"39fc8e98","apps_chroma_index.md":"86d30916","apps_chroma_profile_index.md":"ea3df796","apps_chroma_roll_index.md":"1eea5ad9","apps_chroma_split_index.md":"fb888229","apps_chroma_waveform_index.md":"53dd9169","apps_color_cmyk_index.md":"d6ed0426","apps_color_hsl_index.md":"d619aecf","apps_color_index.md":"f359b8f2","apps_color_lab_index.md":"40586eb8","apps_color_rgb_index.md":"c0d08ed0","apps_experiment_ambience_index.md":"42c9f38b","apps_experiment_dev_index.md":"5912218d","apps_experiment_fretboard_index.md":"ab42c245","apps_experiment_index.md":"d9ef31da","apps_experiment_lab_index.md":"36a9c50e","apps_experiment_other_index.md":"aaa79f9b","apps_experiment_paper_index.md":"cb107d33","apps_experiment_spectrum_index.md":"2ed5fd70","apps_experiment_touchme_index.md":"f051fd9a","apps_index.md":"f6916d8e","apps_midi_index.md":"2eb7c19c","apps_midi_log_index.md":"8011436b","apps_midi_monitor_index.md":"dd7ad296","apps_midi_radar_index.md":"9e87703e","apps_midi_recorder_index.md":"655555bc","apps_midi_roll_index.md":"da5e616c","apps_midi_router_index.md":"ea30ee97","apps_midi_visualizer_index.md":"dc768c56","apps_pitch_drone_index.md":"5a9c1cf1","apps_pitch_grid_index.md":"09f50df1","apps_pitch_index.md":"63a19289","apps_pitch_roll_index.md":"5b7dee28","apps_pitch_spectrogram_index.md":"79fa9016","apps_pitch_table_index.md":"972311a1","apps_pitch_tuner_index.md":"d2d407c7","apps_rhythm_circle_index.md":"7c7cad55","apps_rhythm_index.md":"63dd7565","apps_rhythm_loops_index.md":"51ec1b2a","apps_rhythm_noise_index.md":"82716138","apps_rhythm_sequencer_index.md":"b92ed5ff","apps_sound_dissonance_index.md":"d9871f94","apps_sound_index.md":"f611d91b","apps_sound_loudness_index.md":"576c0ad5","apps_sound_monochord_index.md":"28691c82","apps_sound_overtones_index.md":"8aedbe4f","contact_author_index.md":"66a88326","contact_index.md":"cec307dc","contact_official_index.md":"765399ae","index.md":"a319ce84","shop_fretboard_a5multi_index.md":"22ae18d0","shop_fretboard_guitar_index.md":"205d68b4","shop_fretboard_index.md":"53003f7b","shop_fretboard_tenor_index.md":"9f0ea685","shop_fretboard_ukulele_index.md":"9b64497a","shop_index.md":"c6c9dc0c","shop_keys_108_index.md":"a533013b","shop_keys_a5max_index.md":"344a7744","shop_keys_index.md":"26301e21","shop_keys_op-1_index.md":"b31411b5","shop_keys_op-1_matte_index.md":"f973dfa7","shop_keys_piano_index.md":"650bb424","shop_keys_universal_index.md":"6f9cebc2","shop_memo_a4_index.md":"8fc8f4a5","shop_memo_a5_index.md":"ad38e999","shop_memo_holocircle_index.md":"e2068e74","shop_memo_index.md":"10550dda","support_contribute_index.md":"7afc5f14","support_donate_index.md":"12520c31","support_follow_index.md":"3f25c1f5","support_index.md":"314ed89e","theory_chords_5more_index.md":"77b92726","theory_chords_clusters_index.md":"8527a61c","theory_chords_index.md":"12548319","theory_chords_tetrads_index.md":"b4593606","theory_chords_triads_index.md":"a931ecaa","theory_color_index.md":"99a1e002","theory_color_interplay_index.md":"ec66cdd7","theory_color_interplay_spectrum_index.md":"414231e3","theory_color_interplay_synesthesia_index.md":"7d99f11d","theory_color_light_em-waves_index.md":"0294773b","theory_color_light_index.md":"21722efc","theory_color_light_spectrum_index.md":"6d5ec6a6","theory_color_light_sun_index.md":"621abf82","theory_color_models_additive_index.md":"addf72b2","theory_color_models_index.md":"ebce2968","theory_color_models_perceptual_index.md":"cdc55528","theory_color_models_subtractive_index.md":"d8952f2b","theory_color_names_index.md":"d8ad1357","theory_color_perception_index.md":"a6ea5abd","theory_composition_composers_index.md":"996882e0","theory_composition_form_index.md":"f6036855","theory_composition_generative_index.md":"dc609fd7","theory_composition_index.md":"9cce049b","theory_composition_serialism_index.md":"50a8624c","theory_composition_song_index.md":"1b4d6f16","theory_composition_texture_index.md":"a01b5d54","theory_harmony_chord-scale_index.md":"9f098032","theory_harmony_index.md":"b3e90420","theory_harmony_modulation_index.md":"cc7c13ee","theory_harmony_movement_index.md":"fce138fa","theory_harmony_non-chord_index.md":"ebac6f18","theory_harmony_polytonality_index.md":"835b4a3f","theory_harmony_progressions_index.md":"65a7597a","theory_harmony_study_index.md":"aad755cf","theory_index.md":"3f2ca2e4","theory_intervals_cycles_index.md":"d0ffb646","theory_intervals_emancipation_index.md":"997b27fc","theory_intervals_fifth-fourth_index.md":"90f4f04f","theory_intervals_index.md":"ff5dc125","theory_intervals_second-seventh_index.md":"aed8ec8d","theory_intervals_third-sixth_index.md":"0278322d","theory_intervals_unison-octave_index.md":"4e63ad01","theory_melody_articulation_index.md":"5ad9db06","theory_melody_drone_index.md":"880e6ca9","theory_melody_index.md":"34bbbb0f","theory_melody_motion_index.md":"c10f8b1a","theory_melody_singing_index.md":"7cefcff1","theory_melody_study_index.md":"a3ef401e","theory_notes_alternative_abc_index.md":"ff800a6a","theory_notes_alternative_bilinear_index.md":"88dbcd83","theory_notes_alternative_chromatic-staff_index.md":"6590a247","theory_notes_alternative_dodeka_index.md":"a1306e54","theory_notes_alternative_index.md":"633360ab","theory_notes_alternative_integer_index.md":"451c2551","theory_notes_alternative_klavar_index.md":"0ac89f52","theory_notes_alternative_midi_index.md":"306672b0","theory_notes_alternative_numbered_index.md":"d3132c02","theory_notes_alternative_parsons_index.md":"8ba30948","theory_notes_alternative_piano-roll_index.md":"ae1175ee","theory_notes_alternative_scientific_index.md":"1683bb3a","theory_notes_alternative_tabulature_index.md":"99c6ac3a","theory_notes_color_index.md":"2ae21e15","theory_notes_evolution_index.md":"2befa6cb","theory_notes_index.md":"232edd4d","theory_notes_national_index.md":"3b92f92c","theory_notes_solmization_index.md":"65838d0c","theory_notes_staff_index.md":"a52ccfe9","theory_notes_staff_sight-reading_index.md":"a5b94b45","theory_notes_temperaments_equal_index.md":"60767a16","theory_notes_temperaments_index.md":"05c25cab","theory_notes_temperaments_just_index.md":"e54a4e99","theory_notes_temperaments_pythagorean_index.md":"2e6a637f","theory_notes_temperaments_tunings_index.md":"785c8a09","theory_resources_index.md":"14e0db0a","theory_rhythm_counting_index.md":"fccad471","theory_rhythm_groove_index.md":"5ce6577c","theory_rhythm_index.md":"88f7862e","theory_rhythm_meter_complex_index.md":"a50af9ef","theory_rhythm_meter_compound_index.md":"065d83ee","theory_rhythm_meter_index.md":"fc4c7fec","theory_rhythm_meter_simple_index.md":"9958d55f","theory_rhythm_meter_time_index.md":"bd0ab9a5","theory_rhythm_pulse_index.md":"0150c0ca","theory_rhythm_rudiments_index.md":"92095374","theory_rhythm_study_index.md":"90298e71","theory_rhythm_system_clave_index.md":"770df247","theory_rhythm_system_crossbeat_index.md":"d4e6d5a4","theory_rhythm_system_euclidean_index.md":"eaf44c9f","theory_rhythm_system_flamenco_index.md":"b438a0dc","theory_rhythm_system_index.md":"c5d7e3b9","theory_rhythm_system_tala_index.md":"aa4e7004","theory_scales_degrees_index.md":"804c752b","theory_scales_diatonic_index.md":"46ba8ee7","theory_scales_index.md":"fc22aca7","theory_scales_pentatonic_index.md":"8df4c4e1","theory_scales_raga_index.md":"8bd6fe57","theory_scales_study_index.md":"4448708e","theory_scales_symmetrical_index.md":"6ab6a3a1","theory_sound_hearing_index.md":"a93b19e7","theory_sound_index.md":"5ad8f420","theory_sound_nature_index.md":"43e501e6","theory_sound_pitch_index.md":"73cda58e","theory_sound_psychoacoustics_illusions_index.md":"c0e217fe","theory_sound_psychoacoustics_index.md":"233f40d5","theory_sound_timbre_index.md":"6e93a290"}
