{"academy_materials_index.md":"13176c64","academy_centers_phuket_index.md":"66942b19","academy_educators_index.md":"7fe28260","academy_materials_dev_index.md":"6d11e48a","academy_collab_apps_index.md":"d6d434c5","academy_index.md":"0da3dd2b","academy_collab_apps_touchme_index.md":"1f062224","404.md":"72df1cec","academy_collab_art_index.md":"79e24e69","academy_collab_art_suzdal_index.md":"5cf63ed3","academy_collab_education_index.md":"6ff50cb4","academy_collab_education_skillbox_index.md":"27fa81b1","academy_collab_video_index.md":"85f41992","academy_centers_index.md":"5bddb369","academy_collab_index.md":"fbf9c5c5","academy_collab_art_programmable_index.md":"8776a38a","academy_collab_video_tsoop_index.md":"6278347f","academy_materials_presentations_index.md":"d17c7c2f","academy_materials_presentations_namm-19_index.md":"b69ae2e3","academy_collab_education_skillbox_notes_index.md":"a3223be0","contact_author_index.md":"5710a64e","academy_materials_presentations_colab-20_index.md":"3ae1ecdf","contact_index.md":"91a70c67","practice_chord_array_index.md":"d6865dc1","index.md":"0271a385","practice_chord_index.md":"87fea274","practice_chord_modes_index.md":"10c50527","practice_chord_scales_index.md":"6a26dfe2","practice_chroma_browser__index.md":"76fbdc93","practice_chord_fifths_index.md":"cc94d4f7","practice_chroma_compass_index.md":"fa854225","practice_chroma_shader_index.md":"8d5295c5","practice_chroma_waveform_index.md":"449a2a03","practice_color_cmyk_index.md":"ee871784","practice_chroma_see_index.md":"41931ae9","practice_chroma_gram_index.md":"fc1ce0a2","practice_color_mix_index.md":"1692d393","practice_color_rgb_index.md":"a8051907","practice_color_lab_index.md":"2e494dff","practice_chroma_index.md":"774be2be","practice_color_index.md":"8b37940b","practice_color_hsl_index.md":"abb70007","practice_chroma_profile_index.md":"c96366cc","practice_chroma_grid_index.md":"b2f49948","practice_experiments_ambience_index.md":"0a02970c","practice_experiments_connect_index.md":"77fc79d9","practice_experiments_dev_index.md":"0ad45af8","practice_experiments_connect_circle_index.md":"17c80248","practice_experiments_index.md":"06ae6ec4","practice_experiments_chuck_index.md":"7c2c9191","practice_experiments_amy_index.md":"d778f90f","practice_experiments_fretboard_index.md":"af382fe6","practice_experiments_other_index.md":"c351719b","practice_experiments_elementary_index.md":"5915b19a","practice_experiments_lab_index.md":"f6bb2acc","practice_experiments_paper_index.md":"7ee4fa6b","practice_experiments_jam-session_index.md":"08d7681a","practice_index.md":"ec5b64f8","practice_midi_index.md":"2b131faa","practice_midi_grid__index.md":"a2a9fdb3","practice_experiments_spectrum_index.md":"ac4c620b","practice_midi_log_index.md":"e9174258","practice_midi_monitor_index.md":"f430bb95","practice_midi_radar_index.md":"3e979127","practice_midi_recorder_index.md":"19c01ce8","practice_midi_roll_index.md":"862a21a7","practice_pitch_index.md":"6471f7ac","practice_midi_visualizer_index.md":"9848bdcb","practice_midi_router_index.md":"783ddda2","practice_midi_rows_index.md":"c8780771","practice_pitch_roll_index.md":"d8755a77","practice_pitch_drone_index.md":"403b75c7","practice_rhythm_bars_index.md":"169af9c0","practice_pitch_tuner_index.md":"cac3a8a6","practice_pitch_table_index.md":"5a96117a","practice_pitch_spectrogram_index.md":"fabf70c0","practice_rhythm_noise_index.md":"fff2f14b","practice_rhythm_index.md":"1ef1bcb3","shop_fretboard_ukulele_index.md":"9d963bfa","practice_rhythm_sequencer_index.md":"2a91c5e0","practice_sound_dissonance_index.md":"7e106b88","practice_sound_index.md":"d7d42af2","shop_fretboard_ukulele-one_index.md":"d96c9638","practice_rhythm_wheel_index.md":"498ef009","shop_keys_op-1_uncoated__index.md":"5e618996","practice_rhythm_circle_index.md":"34e52697","shop_keys_universal_index.md":"d6a5174e","support_code_docs_interfaces_midi.chromanote.md":"c660f1b7","support_code_docs_modules.md":"e698909e","shop_keys_piano_index.md":"9d2506a6","shop_memo_holocircle_index.md":"35d5b48a","practice_sound_monochord_index.md":"8b1190c4","support_code_docs_modules_audio.md":"baf1ed96","practice_sound_loudness_index.md":"b463023f","shop_fretboard_a5multi_index.md":"4b46395d","shop_fretboard_guitar_index.md":"9e85badc","support_code_docs_modules_audiorecorder.md":"0009034b","shop_fretboard_index.md":"50cfcb75","support_code_docs_interfaces_midi.notemessageevent.md":"02d75c06","support_code_docs_interfaces_tuner___pitch_detection.aubiofeature.md":"a86a84c1","support_code_docs_modules_aubio.md":"6f49bf53","support_code_docs_interfaces_sequence.clicksampler.md":"47ee350d","support_code_docs_modules_calculations.md":"a0f6ab70","support_code_docs_interfaces_chroma.namedpitch.md":"a0d17110","shop_success.md":"f545ca35","support_code_docs_interfaces_midi.midiinterface.md":"287833d0","shop_cancel.md":"af7f4ad5","shop_keys_op-1_index.md":"5fbc4a81","support_code_docs_interfaces_tuner___pitch_detection.chain.md":"664c84c3","shop_keys_a5max_index.md":"584a3d9e","shop_keys_index.md":"fde96061","support_code_docs_readme.md":"a728f180","shop_memo_a5_index.md":"a110f36f","shop_memo_index.md":"e0c0b996","shop_memo_a4_index.md":"2fb62e4b","practice_sound_overtones_index.md":"ed0f98cd","support_code_docs_modules_cast___the_video_broadcasting_setup.md":"6b961a7a","support_code_docs_modules_clipboard.md":"ec08c9ff","support_code_docs_modules_chroma.md":"3d18d02a","support_code_docs_modules_keyboard.md":"49d1da09","support_code_docs_modules_colors.md":"739b20dd","support_code_docs_modules_loop.md":"7f6a882e","support_code_docs_modules_midi.md":"90c137b7","support_code_docs_modules_noise_synthesis.md":"e8cb234b","support_code_docs_modules_synth.md":"dec7950f","support_code_docs_modules_piano.md":"c4aa8a6b","support_code_docs_modules_tuner___pitch_detection.md":"e3fb1e64","support_code_docs_modules_microphone.md":"ea6f83e0","theory_composition_composers_index.md":"3ae7b700","theory_color_light_spectrum_index.md":"0667d114","theory_color_models_additive_index.md":"9d0d8621","support_code_docs_modules_tempo.md":"701d2705","theory_composition_index.md":"2f565bf3","support_code_docs_modules_musictheory.md":"09656b77","theory_composition_generative_index.md":"4da58554","support_code_docs_modules_mouse.md":"d0018c2e","theory_color_models_index.md":"2941f003","theory_chords_5more_index.md":"ea1a326d","theory_composition_electronic_index.md":"f33f89e9","theory_color_perception_index.md":"fdf26c4f","theory_chords_clusters_index.md":"a5dd5757","support_code_docs_modules_sequence.md":"25786d48","support_code_docs_modules_index.md":"aa87c73e","theory_color_models_perceptual_index.md":"acadadbb","theory_color_index.md":"c2bf9983","theory_color_interplay_spectrum_index.md":"ab75e5f3","theory_chords_tetrads_index.md":"c4adbaf6","theory_color_light_index.md":"d0c75d5c","theory_chords_index.md":"4c51fb6a","theory_color_light_sun_index.md":"16c155d9","theory_color_names_index.md":"13e5f1c1","theory_color_models_subtractive_index.md":"e17715e3","theory_melody_articulation_index.md":"41f408b0","support_sponsor_index.md":"81609e1f","theory_color_interplay_synesthesia_index.md":"12405286","theory_color_light_em-waves_index.md":"f392c9c8","support_code_index.md":"49b741e2","theory_composition_form_index.md":"a95daf58","theory_intervals_cycles_index.md":"e715883a","theory_intervals_dissonance_index.md":"2e0bc1f9","theory_notes_color_index.md":"d45f192f","theory_intervals_emancipation_index.md":"c0ff954b","theory_notes_alternative_numbered_index.md":"b3109165","theory_notes_alternative_parsons_index.md":"7286d6da","theory_notes_alternative_piano-roll_index.md":"33dd0227","theory_notes_alternative_ring-tone_index.md":"733f5628","theory_notes_alternative_scientific_index.md":"669addc7","theory_intervals_index.md":"40af8c9b","theory_scales_diatonic_index.md":"ca71da10","theory_scales_index.md":"89562a6b","theory_sound_hearing_index.md":"b39bc64d","theory_notes_solmization_index.md":"cba81c7c","theory_notes_staff_sight-reading_index.md":"846f7567","theory_notes_temperaments_equal_index.md":"cfa3cd00","theory_color_interplay_index.md":"7b9253d0","theory_scales_symmetrical_index.md":"019386bb","theory_composition_sound-painting_index.md":"474e6826","theory_chords_triads_index.md":"87796c51","theory_melody_motif_index.md":"eb428b87","theory_harmony_functional_index.md":"fa70bd74","theory_composition_texture_index.md":"237c6261","theory_harmony_chord-scale_index.md":"4a79430e","theory_composition_song_index.md":"32923dd8","theory_scales_pentatonic_index.md":"0249a89a","theory_harmony_modulation_index.md":"3fc58438","theory_scales_study_index.md":"2755f525","theory_sound_psychoacoustics_index.md":"3889ae27","theory_harmony_index.md":"ba84afe6","support_index.md":"08ebb0d0","theory_melody_study_index.md":"488c2b45","theory_rhythm_counting_index.md":"444a9e6d","theory_rhythm_system_index.md":"ebc3f5aa","theory_rhythm_meter_simple_index.md":"1a46b49a","theory_notes_alternative_midi_index.md":"07acd7a2","theory_notes_alternative_abc_index.md":"40b14199","theory_melody_motion_index.md":"4d6fa744","theory_sound_psychoacoustics_illusions_index.md":"48345eb3","theory_notes_temperaments_index.md":"f1dc2775","theory_notes_alternative_dodeka_index.md":"e4e57dd6","theory_notes_temperaments_pythagorean_index.md":"9d73af88","theory_harmony_non-chord_index.md":"afa95964","theory_notes_alternative_index.md":"0e5a5ea5","theory_rhythm_system_crossbeat_index.md":"e7c84f7c","theory_notes_alternative_klavar_index.md":"452709eb","theory_notes_alternative_chromatic-staff_index.md":"5bab70db","theory_sound_pitch_index.md":"b23c8669","theory_melody_singing_index.md":"efbcf91f","support_follow_index.md":"6d9f060c","theory_notes_alternative_tabulature_index.md":"88d8955d","support_code_docs_modules_vite_config.md":"1bdc854d","theory_intervals_fifth-fourth_index.md":"cfea8019","theory_notes_temperaments_just_index.md":"a0378fa4","theory_notes_staff_index.md":"92b8bba9","theory_rhythm_rudiments_index.md":"9d1503b8","theory_sound_nature_index.md":"11fc6c9b","theory_intervals_third-sixth_index.md":"2f326848","theory_intervals_second-seventh_index.md":"42e16aa4","theory_rhythm_system_clave_index.md":"f9d99ed3","theory_composition_serialism_index.md":"74fdb84d","support_code_docs_modules_midirender.md":"9904d5aa","theory_intervals_unison-octave_index.md":"cca39d0d","theory_melody_index.md":"a3ae6542","theory_notes_temperaments_tunings_index.md":"c5aa5353","theory_harmony_movement_index.md":"4fb5484d","theory_harmony_study_index.md":"3625a0e1","theory_rhythm_system_flamenco_index.md":"44192177","theory_harmony_progressions_index.md":"e91b0cea","theory_rhythm_groove_index.md":"6c93bfd0","theory_rhythm_index.md":"80252e42","theory_scales_degrees_index.md":"aaad6091","theory_rhythm_meter_complex_index.md":"e4c26170","theory_notes_national_index.md":"172a9349","theory_index.md":"beac0ce5","theory_rhythm_meter_compound_index.md":"adcd765f","theory_notes_index.md":"07090258","theory_notes_evolution_index.md":"bede50f0","theory_harmony_polytonality_index.md":"357d3e61","theory_sound_timbre_index.md":"3754ed42","theory_rhythm_meter_index.md":"a92eef98","theory_melody_drone_index.md":"0608f26e","theory_resources_index.md":"cb264a47","theory_sound_index.md":"4c812eca","theory_rhythm_pulse_index.md":"bf2ff945","theory_scales_raga_index.md":"e916b621","theory_scales_melodic_index.md":"ee6e0ced","theory_notes_alternative_bilinear_index.md":"bf56b1d0","theory_notes_alternative_integer_index.md":"3c54236b","theory_rhythm_study_index.md":"f6cd0627","theory_rhythm_system_tala_index.md":"96df55d2","theory_rhythm_meter_time_index.md":"847fef2d","theory_rhythm_system_euclidean_index.md":"f1b8e782","shop_index.md":"65c1cfba","practice_chord_tabs_index.md":"9e0209cb"}
